mtgdc_banlist/__init__.py
mtgdc_banlist/__main__.py
mtgdc_banlist/banlist_compiler.py
mtgdc_banlist/parser.py
mtgdc_banlist/banlists/2012-01-01.json
mtgdc_banlist/banlists/2015-01-31.json
mtgdc_banlist/banlists/2015-03-23.json
mtgdc_banlist/banlists/2015-07-17.json
mtgdc_banlist/banlists/2015-10-02.json
mtgdc_banlist/banlists/2016-01-22.json
mtgdc_banlist/banlists/2016-04-04.json
mtgdc_banlist/banlists/2016-07-18.json
mtgdc_banlist/banlists/2016-09-22.json
mtgdc_banlist/banlists/2017-01-18.json
mtgdc_banlist/banlists/2017-04-17.json
mtgdc_banlist/banlists/2017-07-17.json
mtgdc_banlist/banlists/2017-09-25.json
mtgdc_banlist/banlists/2017-11-27.json
mtgdc_banlist/banlists/2018-02-26.json
mtgdc_banlist/banlists/2018-05-28.json
mtgdc_banlist/banlists/2018-08-27.json
mtgdc_banlist/banlists/2018-11-26.json
mtgdc_banlist/banlists/2019-02-25.json
mtgdc_banlist/banlists/2019-05-27.json
mtgdc_banlist/banlists/2019-08-26.json
mtgdc_banlist/banlists/2019-11-25.json
mtgdc_banlist/banlists/2020-02-24.json
mtgdc_banlist/banlists/2020-05-25.json
mtgdc_banlist/banlists/2020-08-24.json
mtgdc_banlist/banlists/2020-11-20.json
mtgdc_banlist/banlists/2021-01-21.json
mtgdc_banlist/banlists/2021-03-29.json
mtgdc_banlist/banlists/2021-05-31.json
mtgdc_banlist/banlists/2021-07-26.json
mtgdc_banlist/banlists/2021-09-27.json
mtgdc_banlist/banlists/2021-11-29.json
mtgdc_banlist/banlists/2022-01-31.json
mtgdc_banlist/banlists/2022-02-14.json
mtgdc_banlist/banlists/2022-03-28.json
mtgdc_banlist/banlists/2022-05-30.json
mtgdc_banlist/banlists/2022-07-25.json
mtgdc_banlist/banlists/2022-09-26.json
mtgdc_banlist/banlists/2022-11-28.json
mtgdc_banlist/banlists/2023-01-30.json
mtgdc_banlist/banlists/2023-03-27.json
mtgdc_banlist/banlists/2023-05-29.json
mtgdc_banlist/banlists/2023-07-31.json
mtgdc_banlist/static/banlist_html_footer.html
mtgdc_banlist/static/banlist_html_header.html
mtgdc_banlist-1.2.dist-info/LICENSE
mtgdc_banlist-1.2.dist-info/METADATA
mtgdc_banlist-1.2.dist-info/WHEEL
mtgdc_banlist-1.2.dist-info/top_level.txt
mtgdc_banlist-1.2.dist-info/zip-safe
mtgdc_banlist-1.2.dist-info/RECORD
