Metadata-Version: 2.1
Name: mtgdc-banlist
Version: 1.2
Summary: CLI, new way to help keep an up-to-date MTGDC banlist
Home-page: https://github.com/barrins-codex/mtgdc-banlist
Author: barrins-codex
Author-email: spigushe@gmail.com
License: MIT
Keywords: magic mtg duel-commadner dc
Classifier: Development Status :: 5 - Production/Stable
Classifier: Intended Audience :: Developers
Classifier: License :: OSI Approved :: MIT License
Classifier: Natural Language :: French
Classifier: Operating System :: OS Independent
Classifier: Programming Language :: Python :: 3
Classifier: Programming Language :: Python :: 3.10
Classifier: Topic :: Software Development :: Libraries :: Python Modules
Classifier: Topic :: Games/Entertainment
Requires-Python: >=3.9
License-File: LICENSE
Requires-Dist: requests
Requires-Dist: unidecode
Provides-Extra: dev
Requires-Dist: docutils <0.19 ; extra == 'dev'
Requires-Dist: sphinx <7,>=1.6 ; extra == 'dev'
Requires-Dist: sphinx-rtd-theme ; extra == 'dev'
Requires-Dist: black ; extra == 'dev'
Requires-Dist: flake8 ; extra == 'dev'
Requires-Dist: ipython ; extra == 'dev'
Requires-Dist: pytest ; extra == 'dev'
Requires-Dist: pylint ; extra == 'dev'
Requires-Dist: zest.releaser[recommended] ; extra == 'dev'
